{"model":{"0":"alex","1":"vgg","2":"mob","3":"res","4":"alex","5":"vgg","6":"mob","7":"res","8":"alex","9":"vgg","10":"mob","11":"res","12":"alex","13":"vgg","14":"mob","15":"res","16":"alex","17":"vgg","18":"mob","19":"res","20":"alex","21":"vgg","22":"mob","23":"res","24":"alex","25":"vgg","26":"mob","27":"res","28":"alex","29":"vgg","30":"mob","31":"res","32":"alex","33":"vgg","34":"mob","35":"res","36":"alex","37":"vgg","38":"mob","39":"res","40":"alex","41":"vgg","42":"mob","43":"res","44":"alex","45":"vgg","46":"mob","47":"res","48":"alex","49":"vgg","50":"mob","51":"res","52":"alex","53":"vgg","54":"mob","55":"res","56":"alex","57":"vgg","58":"mob","59":"res","60":"alex","61":"vgg","62":"mob","63":"res","64":"alex","65":"vgg","66":"mob","67":"res","68":"alex","69":"vgg","70":"mob","71":"res","72":"alex","73":"vgg","74":"mob","75":"res","76":"alex","77":"vgg","78":"mob","79":"res","80":"alex","81":"vgg","82":"mob","83":"res","84":"alex","85":"vgg","86":"mob","87":"res","88":"alex","89":"vgg","90":"mob","91":"res","92":"alex","93":"vgg","94":"mob","95":"res","96":"alex","97":"vgg","98":"mob","99":"res","100":"alex","101":"vgg","102":"mob","103":"res","104":"alex","105":"vgg","106":"mob","107":"res","108":"alex","109":"vgg","110":"mob","111":"res","112":"alex","113":"vgg","114":"mob","115":"res","116":"alex","117":"vgg","118":"mob","119":"res","120":"alex","121":"vgg","122":"mob","123":"res","124":"alex","125":"vgg","126":"mob","127":"res","128":"alex","129":"vgg","130":"mob","131":"res","132":"alex","133":"vgg","134":"mob","135":"res","136":"alex","137":"vgg","138":"mob","139":"res","140":"alex","141":"vgg","142":"mob","143":"res","144":"alex","145":"vgg","146":"mob","147":"res","148":"alex","149":"vgg","150":"mob","151":"res","152":"alex","153":"vgg","154":"mob","155":"res","156":"alex","157":"vgg","158":"mob","159":"res","160":"alex","161":"vgg","162":"mob","163":"res","164":"alex","165":"vgg","166":"mob","167":"res","168":"alex","169":"vgg","170":"mob","171":"res","172":"alex","173":"vgg","174":"mob","175":"res","176":"alex","177":"vgg","178":"mob","179":"res","180":"alex","181":"vgg","182":"mob","183":"res","184":"alex","185":"vgg","186":"mob","187":"res","188":"alex","189":"vgg","190":"mob","191":"res","192":"alex","193":"vgg","194":"mob","195":"res","196":"alex","197":"vgg","198":"mob","199":"res","200":"alex","201":"vgg","202":"mob","203":"res","204":"alex","205":"vgg","206":"mob","207":"res","208":"alex","209":"vgg","210":"mob","211":"res","212":"alex","213":"vgg","214":"mob","215":"res","216":"alex","217":"vgg","218":"mob","219":"res","220":"alex","221":"vgg","222":"mob","223":"res","224":"alex","225":"vgg","226":"mob","227":"res","228":"alex","229":"vgg","230":"mob","231":"res","232":"alex","233":"vgg","234":"mob","235":"res","236":"alex","237":"vgg","238":"mob","239":"res","240":"alex","241":"vgg","242":"mob","243":"res","244":"alex","245":"vgg","246":"mob","247":"res","248":"alex","249":"vgg","250":"mob","251":"res","252":"alex","253":"vgg","254":"mob","255":"res","256":"alex","257":"vgg","258":"mob","259":"res","260":"alex","261":"vgg","262":"mob","263":"res","264":"alex","265":"vgg","266":"mob","267":"res","268":"alex","269":"vgg","270":"mob","271":"res","272":"alex","273":"vgg","274":"mob","275":"res","276":"alex","277":"vgg","278":"mob","279":"res","280":"alex","281":"vgg","282":"mob","283":"res","284":"alex","285":"vgg","286":"mob","287":"res","288":"alex","289":"vgg","290":"mob","291":"res","292":"alex","293":"vgg","294":"mob","295":"res","296":"alex","297":"vgg","298":"mob","299":"res","300":"alex","301":"vgg","302":"mob","303":"res","304":"alex","305":"vgg","306":"mob","307":"res","308":"alex","309":"vgg","310":"mob","311":"res","312":"alex","313":"vgg","314":"mob","315":"res","316":"alex","317":"vgg","318":"mob","319":"res","320":"alex","321":"vgg","322":"mob","323":"res","324":"alex","325":"vgg","326":"mob","327":"res","328":"alex","329":"vgg","330":"mob","331":"res","332":"alex","333":"vgg","334":"mob","335":"res","336":"alex","337":"vgg","338":"mob","339":"res","340":"alex","341":"vgg","342":"mob","343":"res","344":"alex","345":"vgg","346":"mob","347":"res","348":"alex","349":"vgg","350":"mob","351":"res","352":"alex","353":"vgg","354":"mob","355":"res","356":"alex","357":"vgg","358":"mob","359":"res","360":"alex","361":"vgg","362":"mob","363":"res","364":"alex","365":"vgg","366":"mob","367":"res","368":"alex","369":"vgg","370":"mob","371":"res","372":"alex","373":"vgg","374":"mob","375":"res","376":"alex","377":"vgg","378":"mob","379":"res","380":"alex","381":"vgg","382":"mob","383":"res","384":"alex","385":"vgg","386":"mob","387":"res","388":"alex","389":"vgg","390":"mob","391":"res","392":"alex","393":"vgg","394":"mob","395":"res","396":"alex","397":"vgg","398":"mob","399":"res"},"perf":{"0":71.6112442017,"1":21.507358551,"2":44.5472679138,"3":98.2910461426,"4":49.2211837769,"5":66.1653366089,"6":58.2677230835,"7":98.8306732178,"8":76.1652450562,"9":37.5276641846,"10":36.1485557556,"11":30.9103603363,"12":98.3661727905,"13":61.9342155457,"14":90.5860137939,"15":92.5949783325,"16":92.3963241577,"17":91.4600219727,"18":95.5842666626,"19":91.8622283936,"20":80.7636947632,"21":80.184677124,"22":64.449256897,"23":50.5625,"24":8.6007213593,"25":17.8783187866,"26":29.6314296722,"27":16.1203479767,"28":32.4615020752,"29":79.213104248,"30":57.3616790771,"31":88.6837997437,"32":31.7017288208,"33":57.1230125427,"34":51.9736213684,"35":61.7313499451,"36":89.188583374,"37":85.9220046997,"38":64.4457855225,"39":79.417755127,"40":45.5393981934,"41":70.1482086182,"42":77.6234512329,"43":99.9996185303,"44":96.3838195801,"45":99.5273971558,"46":99.4477005005,"47":99.9882659912,"48":99.1183776855,"49":99.9268112183,"50":99.9149932861,"51":99.9952545166,"52":97.0757522583,"53":97.4875488281,"54":98.3807220459,"55":99.9970932007,"56":99.5174255371,"57":99.9210357666,"58":99.6666107178,"59":99.9992752075,"60":79.9447097778,"61":98.5949020386,"62":94.0249633789,"63":99.7144851685,"64":99.9923248291,"65":99.9863586426,"66":99.9690170288,"67":99.9993209839,"68":99.9715499878,"69":99.905090332,"70":98.4544219971,"71":99.9761276245,"72":63.7150688171,"73":75.5388412476,"74":78.9307327271,"75":99.8852157593,"76":20.8341369629,"77":52.5435562134,"78":77.0959014893,"79":99.3906326294,"80":98.8209152222,"81":99.734916687,"82":91.9568481445,"83":99.8713226318,"84":99.9044723511,"85":99.8285140991,"86":99.9999847412,"87":99.9996032715,"88":99.8579406738,"89":99.9667434692,"90":99.8545913696,"91":99.9999771118,"92":98.7535247803,"93":99.6056289673,"94":99.9858856201,"95":100.0,"96":97.2859344482,"97":99.8064193726,"98":81.546333313,"99":99.8246459961,"100":37.4740943909,"101":81.719543457,"102":54.0833892822,"103":99.9519729614,"104":97.2722473145,"105":97.9815750122,"106":99.3417129517,"107":99.9999542236,"108":99.9739837646,"109":99.9994888306,"110":99.9998245239,"111":100.0,"112":99.5964431763,"113":99.6262741089,"114":98.3071136475,"115":99.9999847412,"116":7.6817922592,"117":92.0193099976,"118":98.9918518066,"119":99.998878479,"120":99.9668502808,"121":99.9445343018,"122":99.8432540894,"123":99.9999847412,"124":98.9819946289,"125":99.8641052246,"126":99.4950637817,"127":99.9873886108,"128":99.3750534058,"129":99.8587875366,"130":99.3213882446,"131":99.9901275635,"132":23.5411300659,"133":12.928694725,"134":5.449136734,"135":99.9012680054,"136":45.4663696289,"137":27.0245456696,"138":74.168510437,"139":98.4638977051,"140":97.7921066284,"141":99.8474273682,"142":99.8436889648,"143":100.0,"144":99.9637374878,"145":98.1836853027,"146":97.5424880981,"147":99.9870986938,"148":55.9225540161,"149":98.8799667358,"150":94.4132080078,"151":100.0,"152":51.6660499573,"153":99.9108505249,"154":99.9653930664,"155":100.0,"156":99.3630371094,"157":99.3458557129,"158":99.8042221069,"159":99.9841690063,"160":98.5853652954,"161":98.0072021484,"162":99.5450286865,"163":99.9991912842,"164":100.0,"165":100.0,"166":100.0,"167":100.0,"168":99.7606887817,"169":99.6216583252,"170":99.7513427734,"171":100.0,"172":99.8966369629,"173":99.9995574951,"174":99.9974822998,"175":100.0,"176":99.9976196289,"177":99.9999847412,"178":99.9992752075,"179":100.0,"180":99.9999389648,"181":100.0,"182":99.9998779297,"183":100.0,"184":99.4656906128,"185":99.9970550537,"186":99.9788665771,"187":100.0,"188":97.8631362915,"189":99.9624481201,"190":98.8268051147,"191":100.0,"192":99.9445114136,"193":99.9867324829,"194":99.9764175415,"195":99.9998474121,"196":99.9957580566,"197":99.9999771118,"198":99.9998931885,"199":100.0,"200":99.997177124,"201":99.9893417358,"202":99.9998779297,"203":100.0,"204":31.6015453339,"205":99.7972335815,"206":14.1376810074,"207":99.4884796143,"208":99.9951095581,"209":100.0,"210":99.9999771118,"211":99.999961853,"212":99.9989395142,"213":99.9999160767,"214":99.9962768555,"215":99.9999160767,"216":99.8591461182,"217":100.0,"218":99.9990005493,"219":100.0,"220":83.2937393188,"221":98.1002655029,"222":96.6989974976,"223":99.0783843994,"224":99.9917602539,"225":99.9992370605,"226":99.9991149902,"227":100.0,"228":89.3817062378,"229":99.986289978,"230":96.1010513306,"231":99.9902038574,"232":79.6969299316,"233":99.7574234009,"234":98.712638855,"235":99.9867553711,"236":99.71484375,"237":99.9995498657,"238":99.9828720093,"239":99.9746246338,"240":99.9499664307,"241":99.9990692139,"242":99.9587860107,"243":99.9842681885,"244":99.9996643066,"245":99.9984588623,"246":99.999786377,"247":99.9999771118,"248":99.9988555908,"249":99.9831771851,"250":99.9991531372,"251":99.9999847412,"252":99.9773101807,"253":31.7724170685,"254":98.2274017334,"255":99.9994277954,"256":99.9995574951,"257":99.9998931885,"258":99.9999313354,"259":100.0,"260":99.9894485474,"261":99.9994049072,"262":99.9642333984,"263":99.999961853,"264":99.1781082153,"265":99.9978637695,"266":99.9999847412,"267":100.0,"268":99.9994659424,"269":100.0,"270":99.9998703003,"271":100.0,"272":99.5683441162,"273":99.9614334106,"274":99.9997940063,"275":99.9954452515,"276":99.999961853,"277":100.0,"278":99.9999160767,"279":100.0,"280":66.4212265015,"281":54.543346405,"282":77.4011459351,"283":99.8725357056,"284":99.9713363647,"285":99.9724197388,"286":98.8300476074,"287":99.9702529907,"288":72.6555862427,"289":99.0508575439,"290":84.3700942993,"291":99.9763336182,"292":98.4699172974,"293":96.5350952148,"294":94.7555389404,"295":100.0,"296":99.8659973145,"297":100.0,"298":99.9644165039,"299":100.0,"300":99.9408950806,"301":99.5252456665,"302":98.4340057373,"303":99.9930648804,"304":97.1307067871,"305":99.1477813721,"306":97.6930770874,"307":99.9964141846,"308":88.3213272095,"309":91.1837158203,"310":99.7891616821,"311":99.9910354614,"312":96.0052108765,"313":99.9963531494,"314":99.9712677002,"315":100.0,"316":99.5480651855,"317":99.9881591797,"318":99.8860473633,"319":99.9999847412,"320":0.4952026606,"321":55.018951416,"322":13.8736886978,"323":99.963104248,"324":83.9676742554,"325":96.7923736572,"326":99.8954315186,"327":99.9999847412,"328":99.9780502319,"329":99.9618148804,"330":99.9414291382,"331":99.9999771118,"332":99.9834442139,"333":99.9995498657,"334":99.9764480591,"335":100.0,"336":82.3477783203,"337":49.5859260559,"338":16.5565376282,"339":99.6978378296,"340":93.5482711792,"341":99.9728622437,"342":87.85496521,"343":99.1137008667,"344":75.1580886841,"345":99.3554458618,"346":95.304397583,"347":100.0,"348":99.8666610718,"349":99.9992218018,"350":99.9957885742,"351":100.0,"352":90.2473831177,"353":99.8897781372,"354":94.5120925903,"355":99.5467224121,"356":95.2393798828,"357":99.7262496948,"358":99.6500701904,"359":99.9887466431,"360":97.5531387329,"361":96.205368042,"362":96.4030380249,"363":99.6485595703,"364":27.9680080414,"365":13.6196298599,"366":24.0822200775,"367":65.4518661499,"368":16.3722190857,"369":10.3462543488,"370":0.2982207239,"371":16.5230331421,"372":98.1614227295,"373":75.4001159668,"374":88.0052947998,"375":99.3665313721,"376":38.5557060242,"377":14.8783950806,"378":31.6909275055,"379":77.806930542,"380":87.7532119751,"381":96.6563873291,"382":93.0774841309,"383":99.5213851929,"384":55.5827484131,"385":61.8130607605,"386":74.1015548706,"387":31.1026039124,"388":63.5156860352,"389":54.3359947205,"390":76.9443359375,"391":99.857673645,"392":64.1427841187,"393":78.5481948853,"394":58.2821731567,"395":80.5616531372,"396":90.9805145264,"397":94.2875747681,"398":82.6266021729,"399":98.6054992676},"fps":{"0":124.4600593472,"1":152.4647037441,"2":104.3982477101,"3":23.6634771619,"4":383.3915904936,"5":142.3438539333,"6":133.9434118924,"7":33.1833098625,"8":370.1291916696,"9":155.9684664584,"10":153.6093755722,"11":32.9650174873,"12":368.6976090014,"13":163.7568422286,"14":152.3096811678,"15":34.4880936719,"16":359.8407687028,"17":161.9860193875,"18":151.058993013,"19":35.1797357937,"20":369.9985885674,"21":135.5362243909,"22":150.037703452,"23":36.1634046662,"24":375.6317392083,"25":135.9403642964,"26":153.1997954562,"27":36.1163838013,"28":378.8892502258,"29":151.7256547533,"30":153.2613731867,"31":35.7537144854,"32":369.0869412179,"33":155.8815178206,"34":154.4067147695,"35":36.4975983293,"36":371.1116616528,"37":157.5680528945,"38":151.0481129358,"39":36.3180936548,"40":370.6197755589,"41":154.554646621,"42":151.9290035136,"43":35.661604911,"44":368.3414419953,"45":172.7757455924,"46":155.673236091,"47":36.6715103825,"48":354.6380316226,"49":172.0740102564,"50":154.7256898333,"51":36.4563581052,"52":365.8993282736,"53":162.5006392623,"54":153.8968224848,"55":36.2851037693,"56":370.3906746733,"57":164.4631611967,"58":136.5333333333,"59":36.5771692683,"60":366.7311357874,"61":166.27567889,"62":153.8403755869,"63":35.580227853,"64":367.8891325322,"65":164.8121340721,"66":153.6431371112,"67":34.8639208678,"68":361.9836023129,"69":173.0109309904,"70":152.0942814664,"71":35.7296532924,"72":375.9347494846,"73":173.669992961,"74":147.4272056239,"75":35.9150568571,"76":368.535629558,"77":174.3630845978,"78":151.5611765556,"79":36.099908767,"80":375.6317392083,"81":173.6484226215,"82":152.8202288129,"83":36.5774882488,"84":375.1949190446,"85":172.7543968038,"86":153.1662284546,"87":36.1282053491,"88":370.5542892482,"89":172.5980000823,"90":151.4462538364,"91":36.4760148885,"92":371.6048551431,"93":172.2577518584,"94":153.7276059229,"95":36.3357128006,"96":388.901622624,"97":173.8139322863,"98":151.8245131398,"99":35.1965628357,"100":368.9246195796,"101":174.023068625,"102":150.6845338602,"103":36.5312940931,"104":379.4033469019,"105":174.051954519,"106":150.3550329796,"107":35.9828420439,"108":370.9475546122,"109":174.4646229358,"110":151.2387408503,"111":36.5554916418,"112":372.9927967986,"113":172.982389574,"114":152.4868755908,"115":36.4665008955,"116":374.2575176229,"117":170.5140255305,"118":153.3454226382,"119":36.4960104416,"120":373.1919209894,"121":173.0823257541,"122":152.7311921928,"123":36.5020451499,"124":373.823885918,"125":173.7923261788,"126":152.0336378135,"127":36.3864632041,"128":370.3252692919,"129":173.5621948192,"130":152.5756275009,"131":36.3934090534,"132":379.7812386816,"133":174.2833873515,"134":152.8480740498,"135":36.2995491012,"136":370.783592645,"137":173.9941923173,"138":152.5589786491,"139":36.5979145762,"140":353.4426561052,"141":170.5903119535,"142":152.2820317322,"143":36.4440042054,"144":382.831690398,"145":146.4849649006,"146":152.5035087081,"147":36.4626966878,"148":374.3243195002,"149":157.0077113124,"150":153.8629493764,"151":36.4988687389,"152":340.6402988711,"153":172.6193102313,"154":154.7485242031,"155":36.4411544944,"156":380.2632819583,"157":167.8796029459,"158":152.6978302024,"159":36.5500762494,"160":356.4463329651,"161":173.0823257541,"162":151.6159629844,"163":35.2601783898,"164":372.8270222222,"165":174.5880785881,"166":152.2046666909,"167":35.4686014849,"168":373.324788607,"169":173.5119348033,"170":150.9393983014,"171":35.9264392233,"172":356.4160435078,"173":172.4631578947,"174":150.1075084103,"175":36.3394905562,"176":368.4385101897,"177":172.3993587899,"178":152.653370214,"179":36.469037475,"180":373.1255226403,"181":171.9611332049,"182":154.5034073747,"183":36.3180936548,"184":380.8502678653,"185":173.8643674349,"186":152.398226873,"187":36.6036635919,"188":372.1984204455,"189":173.4115020466,"190":153.4407901957,"191":36.6174046655,"192":374.9266112452,"193":148.1458038994,"194":152.3594754622,"195":36.5739797698,"196":382.0992985333,"197":158.9594481922,"198":153.0600299237,"199":36.5982339185,"200":373.1255226403,"201":159.0920952814,"202":152.2046666909,"203":36.6023858767,"204":351.6941137012,"205":156.8667813599,"206":149.9840514929,"207":36.1733850798,"208":366.3147598253,"209":171.3499468911,"210":154.5831275568,"211":36.411101369,"212":367.0841939436,"213":172.725939958,"214":153.975917768,"215":36.4588932738,"216":371.1445004867,"217":163.9937441351,"218":152.4148406555,"219":36.4995039769,"220":365.0395126197,"221":163.5716402777,"222":147.6347764872,"223":36.1609104233,"224":372.0663532334,"225":156.1077862141,"226":153.2053913869,"227":34.9411774507,"228":367.598948291,"229":163.5078746297,"230":151.1896763031,"231":36.1275829694,"232":367.5345250613,"233":165.3840148259,"234":151.522849608,"235":36.2744341719,"236":355.7509754029,"237":145.7924849665,"238":151.4189169675,"239":36.4430542523,"240":383.4266386324,"241":148.177206246,"242":152.4868755908,"243":36.5975952393,"244":378.4106820642,"245":145.6912015006,"246":152.3207437536,"247":36.6920418857,"248":378.7865980312,"249":151.440785673,"250":153.0767883212,"251":36.55740334,"252":377.4231980563,"253":171.5602094241,"254":152.3760807963,"255":36.503951262,"256":385.151882461,"257":157.3906713197,"258":153.3902867174,"259":30.775299366,"260":374.0238986981,"261":168.7237620178,"262":154.117361749,"263":36.5293851245,"264":344.2186294625,"265":172.1163773647,"266":141.9824650486,"267":36.5542172875,"268":352.6403228519,"269":164.2377633331,"270":150.9393983014,"271":36.2913829355,"272":370.7180484356,"273":173.7059554378,"274":151.7201663954,"275":36.3650109677,"276":376.6098590285,"277":174.3920834893,"278":152.9149440373,"279":36.0707258342,"280":378.6498149318,"281":174.0014104957,"282":148.1301077168,"283":35.9887082243,"284":376.9822038468,"285":148.8661579414,"286":152.7923937197,"287":36.2189907084,"288":373.324788607,"289":159.7890967275,"290":153.1774158206,"291":36.1637164708,"292":363.8677886701,"293":143.0429029398,"294":152.6922712876,"295":36.4645986924,"296":365.7397976979,"297":149.7484380021,"298":152.3705452828,"299":36.5262039537,"300":356.0227484933,"301":168.9072164948,"302":152.5811779257,"303":36.122604704,"304":371.2759139595,"305":155.5635338625,"306":137.8526260435,"307":36.3212386775,"308":359.1936285005,"309":174.0086292731,"310":148.9930730702,"311":35.6485716957,"312":365.5485445355,"313":173.2252921984,"314":153.250173554,"315":35.1924283868,"316":377.5251125113,"317":173.1823774722,"318":154.2477199176,"319":35.287767121,"320":372.0663532334,"321":173.0180678162,"322":153.9533108207,"323":35.4653024986,"324":372.2314518992,"325":172.9110772148,"326":152.8536443149,"327":35.8080472625,"328":368.8921723835,"329":164.4567126725,"330":153.1550427226,"331":36.3861475467,"332":351.0759186407,"333":135.6765219642,"334":152.5256918433,"335":36.459527121,"336":374.7591136526,"337":146.74120981,"338":153.3510292128,"339":36.5134848089,"340":369.8680776014,"341":172.2931317779,"342":148.7816679082,"343":36.3256426245,"344":361.952364515,"345":171.419977113,"346":153.3902867174,"347":36.1883660334,"348":370.9803644083,"349":172.0740102564,"350":154.7142751752,"351":36.5456177191,"352":373.5575347346,"353":155.7830931511,"354":153.8234495911,"355":36.4715744074,"356":363.994098759,"357":172.6051028807,"358":153.9250614701,"359":36.3030051239,"360":368.9570724842,"361":173.2968640251,"362":154.6002211574,"363":36.3981463804,"364":350.8409870347,"365":171.9611332049,"366":153.1997954562,"367":36.4402046898,"368":364.9442269207,"369":162.2931434762,"370":150.5277060006,"371":35.4066232769,"372":351.252323926,"373":164.8574797579,"374":152.8202288129,"375":35.4701012271,"376":373.1919209894,"377":173.6556121393,"378":149.3006798847,"379":36.1668348122,"380":374.2575176229,"381":173.4473575387,"382":150.1343737696,"383":36.4855338471,"384":375.1278060996,"385":174.2689047698,"386":152.0722236322,"387":36.2929530666,"388":376.3057599139,"389":174.9521982147,"390":153.5868761214,"391":36.5615460386,"392":370.783592645,"393":174.3558363818,"394":150.5439144324,"395":36.5672836331,"396":371.5390202852,"397":171.412971515,"398":148.0516766678,"399":36.4985511282},"time":{"0":0.0080347061,"1":0.0065588951,"2":0.0095787048,"3":0.0422592163,"4":0.0026082993,"5":0.0070252419,"6":0.0074658394,"7":0.0301356316,"8":0.0027017593,"9":0.0064115524,"10":0.0065100193,"11":0.0303351879,"12":0.0027122498,"13":0.0061066151,"14":0.0065655708,"15":0.0289955139,"16":0.002779007,"17":0.0061733723,"18":0.0066199303,"19":0.0284254551,"20":0.002702713,"21":0.0073781013,"22":0.0066649914,"23":0.0276522636,"24":0.0026621819,"25":0.0073561668,"26":0.0065274239,"27":0.0276882648,"28":0.0026392937,"29":0.0065908432,"30":0.0065248013,"31":0.0279691219,"32":0.0027093887,"33":0.0064151287,"34":0.0064764023,"35":0.0273990631,"36":0.0026946068,"37":0.0063464642,"38":0.0066204071,"39":0.0275344849,"40":0.0026981831,"41":0.0064702034,"42":0.0065820217,"43":0.0280413628,"44":0.0027148724,"45":0.0057878494,"46":0.0064237118,"47":0.027269125,"48":0.0028197765,"49":0.0058114529,"50":0.0064630508,"51":0.0274300575,"52":0.0027329922,"53":0.0061538219,"54":0.00649786,"55":0.0275595188,"56":0.002699852,"57":0.006080389,"58":0.0073242188,"59":0.0273394585,"60":0.0027267933,"61":0.0060141087,"62":0.0065002441,"63":0.0281054974,"64":0.0027182102,"65":0.0060675144,"66":0.0065085888,"67":0.0286829472,"68":0.0027625561,"69":0.0057799816,"70":0.0065748692,"71":0.027987957,"72":0.0026600361,"73":0.0057580471,"74":0.0067830086,"75":0.0278434753,"76":0.0027134418,"77":0.0057351589,"78":0.0065979958,"79":0.027700901,"80":0.0026621819,"81":0.0057587624,"82":0.0065436363,"83":0.02733922,"84":0.0026652813,"85":0.0057885647,"86":0.0065288544,"87":0.0276792049,"88":0.0026986599,"89":0.0057938099,"90":0.0066030025,"91":0.0274152756,"92":0.0026910305,"93":0.005805254,"94":0.0065050125,"95":0.0275211334,"96":0.0025713444,"97":0.0057532787,"98":0.0065865517,"99":0.0284118652,"100":0.0027105808,"101":0.0057463646,"102":0.0066363811,"103":0.0273737907,"104":0.0026357174,"105":0.0057454109,"106":0.0066509247,"107":0.0277910233,"108":0.0026957989,"109":0.0057318211,"110":0.0066120625,"111":0.0273556709,"112":0.0026810169,"113":0.0057809353,"114":0.0065579414,"115":0.0274224281,"116":0.002671957,"117":0.0058646202,"118":0.006521225,"119":0.0274002552,"120":0.0026795864,"121":0.0057775974,"122":0.006547451,"123":0.0273957253,"124":0.0026750565,"125":0.005753994,"126":0.0065774918,"127":0.027482748,"128":0.0027003288,"129":0.0057616234,"130":0.0065541267,"131":0.0274775028,"132":0.0026330948,"133":0.0057377815,"134":0.0065424442,"135":0.0275485516,"136":0.002696991,"137":0.0057473183,"138":0.006554842,"139":0.0273239613,"140":0.0028293133,"141":0.0058619976,"142":0.0065667629,"143":0.0274393559,"144":0.002612114,"145":0.0068266392,"146":0.0065572262,"147":0.0274252892,"148":0.0026714802,"149":0.0063691139,"150":0.0064992905,"151":0.0273981094,"152":0.002935648,"153":0.0057930946,"154":0.0064620972,"155":0.0274415016,"156":0.0026297569,"157":0.0059566498,"158":0.0065488815,"159":0.027359724,"160":0.0028054714,"161":0.0057775974,"162":0.0065956116,"163":0.0283606052,"164":0.002682209,"165":0.0057277679,"166":0.0065701008,"167":0.0281939507,"168":0.0026786327,"169":0.0057632923,"170":0.0066251755,"171":0.0278346539,"172":0.0028057098,"173":0.0057983398,"174":0.0066618919,"175":0.0275182724,"176":0.0027141571,"177":0.0058004856,"178":0.0065507889,"179":0.0274205208,"180":0.0026800632,"181":0.0058152676,"182":0.0064723492,"183":0.0275344849,"184":0.0026257038,"185":0.0057516098,"186":0.0065617561,"187":0.0273196697,"188":0.002686739,"189":0.0057666302,"190":0.0065171719,"191":0.0273094177,"192":0.0026671886,"193":0.0067501068,"194":0.0065634251,"195":0.0273418427,"196":0.0026171207,"197":0.0062909126,"198":0.0065333843,"199":0.0273237228,"200":0.0026800632,"201":0.0062856674,"202":0.0065701008,"203":0.0273206234,"204":0.00284338,"205":0.006374836,"206":0.0066673756,"207":0.0276446342,"208":0.0027298927,"209":0.00583601,"210":0.0064690113,"211":0.0274641514,"212":0.0027241707,"213":0.0057895184,"214":0.0064945221,"215":0.0274281502,"216":0.0026943684,"217":0.0060977936,"218":0.0065610409,"219":0.0273976326,"220":0.0027394295,"221":0.0061135292,"222":0.0067734718,"223":0.027654171,"224":0.0026876926,"225":0.0064058304,"226":0.0065271854,"227":0.0286195278,"228":0.002720356,"229":0.0061159134,"230":0.0066142082,"231":0.0276796818,"232":0.0027208328,"233":0.0060465336,"234":0.0065996647,"235":0.027567625,"236":0.002810955,"237":0.0068590641,"238":0.0066041946,"239":0.0274400711,"240":0.0026080608,"241":0.0067486763,"242":0.0065579414,"243":0.0273241997,"244":0.0026426315,"245":0.0068638325,"246":0.006565094,"247":0.0272538662,"248":0.0026400089,"249":0.006603241,"250":0.0065326691,"251":0.0273542404,"252":0.0026495457,"253":0.0058288574,"254":0.0065627098,"255":0.0273942947,"256":0.0025963783,"257":0.0063536167,"258":0.0065193176,"259":0.0324935913,"260":0.0026736259,"261":0.0059268475,"262":0.0064885616,"263":0.0273752213,"264":0.0029051304,"265":0.0058100224,"266":0.0070431232,"267":0.0273566246,"268":0.0028357506,"269":0.0060887337,"270":0.0066251755,"271":0.0275547504,"272":0.0026974678,"273":0.005756855,"274":0.0065910816,"275":0.0274989605,"276":0.0026552677,"277":0.0057342052,"278":0.0065395832,"279":0.0277233124,"280":0.0026409626,"281":0.0057470798,"282":0.0067508221,"283":0.0277864933,"284":0.0026526451,"285":0.0067174435,"286":0.0065448284,"287":0.0276098251,"288":0.0026786327,"289":0.0062582493,"290":0.0065283775,"291":0.0276520252,"292":0.002748251,"293":0.0069909096,"294":0.0065491199,"295":0.0274238586,"296":0.0027341843,"297":0.006677866,"298":0.0065629482,"299":0.0273776054,"300":0.0028088093,"301":0.0059204102,"302":0.0065538883,"303":0.0276834965,"304":0.0026934147,"305":0.0064282417,"306":0.0072541237,"307":0.0275321007,"308":0.0027840137,"309":0.0057468414,"310":0.0067117214,"311":0.0280516148,"312":0.0027356148,"313":0.0057728291,"314":0.0065252781,"315":0.0284152031,"316":0.0026488304,"317":0.0057742596,"318":0.006483078,"319":0.0283384323,"320":0.0026876926,"321":0.0057797432,"322":0.0064954758,"323":0.0281965733,"324":0.0026865005,"325":0.0057833195,"326":0.0065422058,"327":0.0279266834,"328":0.0027108192,"329":0.0060806274,"330":0.0065293312,"331":0.0274829865,"332":0.0028483868,"333":0.007370472,"334":0.0065562725,"335":0.0274276733,"336":0.0026683807,"337":0.0068147182,"338":0.0065209866,"339":0.0273871422,"340":0.0027036667,"341":0.0058040619,"342":0.0067212582,"343":0.0275287628,"344":0.0027627945,"345":0.0058336258,"346":0.0065193176,"347":0.0276331902,"348":0.0026955605,"349":0.0058114529,"350":0.0064635277,"351":0.0273630619,"352":0.0026769638,"353":0.0064191818,"354":0.0065009594,"355":0.0274186134,"356":0.0027472973,"357":0.0057935715,"358":0.0064966679,"359":0.027545929,"360":0.0027103424,"361":0.0057704449,"362":0.0064682961,"363":0.0274739265,"364":0.0028502941,"365":0.0058152676,"366":0.0065274239,"367":0.0274422169,"368":0.0027401447,"369":0.0061616898,"370":0.0066432953,"371":0.0282433033,"372":0.0028469563,"373":0.0060658455,"374":0.0065436363,"375":0.0281927586,"376":0.0026795864,"377":0.0057585239,"378":0.0066978931,"379":0.027649641,"380":0.002671957,"381":0.0057654381,"382":0.0066606998,"383":0.027408123,"384":0.0026657581,"385":0.0057382584,"386":0.0065758228,"387":0.0275535583,"388":0.0026574135,"389":0.005715847,"390":0.006510973,"391":0.027351141,"392":0.002696991,"393":0.0057353973,"394":0.00664258,"395":0.0273468494,"396":0.0026915073,"397":0.0058338642,"398":0.0067543983,"399":0.0273983479},"label":{"0":"analog clock","1":"analog clock","2":"analog clock","3":"analog clock","4":"analog clock","5":"analog clock","6":"analog clock","7":"analog clock","8":"analog clock","9":"analog clock","10":"analog clock","11":"analog clock","12":"analog clock","13":"analog clock","14":"analog clock","15":"analog clock","16":"analog clock","17":"analog clock","18":"analog clock","19":"analog clock","20":"analog clock","21":"analog clock","22":"analog clock","23":"analog clock","24":"analog clock","25":"analog clock","26":"analog clock","27":"analog clock","28":"analog clock","29":"analog clock","30":"analog clock","31":"analog clock","32":"analog clock","33":"analog clock","34":"analog clock","35":"analog clock","36":"analog clock","37":"analog clock","38":"analog clock","39":"analog clock","40":"cellular telephone","41":"cellular telephone","42":"cellular telephone","43":"cellular telephone","44":"cellular telephone","45":"cellular telephone","46":"cellular telephone","47":"cellular telephone","48":"cellular telephone","49":"cellular telephone","50":"cellular telephone","51":"cellular telephone","52":"cellular telephone","53":"cellular telephone","54":"cellular telephone","55":"cellular telephone","56":"cellular telephone","57":"cellular telephone","58":"cellular telephone","59":"cellular telephone","60":"cellular telephone","61":"cellular telephone","62":"cellular telephone","63":"cellular telephone","64":"cellular telephone","65":"cellular telephone","66":"cellular telephone","67":"cellular telephone","68":"cellular telephone","69":"cellular telephone","70":"cellular telephone","71":"cellular telephone","72":"cellular telephone","73":"cellular telephone","74":"cellular telephone","75":"cellular telephone","76":"cellular telephone","77":"cellular telephone","78":"cellular telephone","79":"cellular telephone","80":"digital clock","81":"digital clock","82":"digital clock","83":"digital clock","84":"digital clock","85":"digital clock","86":"digital clock","87":"digital clock","88":"digital clock","89":"digital clock","90":"digital clock","91":"digital clock","92":"digital clock","93":"digital clock","94":"digital clock","95":"digital clock","96":"digital clock","97":"digital clock","98":"digital clock","99":"digital clock","100":"digital clock","101":"digital clock","102":"digital clock","103":"digital clock","104":"digital clock","105":"digital clock","106":"digital clock","107":"digital clock","108":"digital clock","109":"digital clock","110":"digital clock","111":"digital clock","112":"digital clock","113":"digital clock","114":"digital clock","115":"digital clock","116":"digital clock","117":"digital clock","118":"digital clock","119":"digital clock","120":"laptop","121":"laptop","122":"laptop","123":"laptop","124":"laptop","125":"laptop","126":"laptop","127":"laptop","128":"laptop","129":"laptop","130":"laptop","131":"laptop","132":"laptop","133":"laptop","134":"laptop","135":"laptop","136":"laptop","137":"laptop","138":"laptop","139":"laptop","140":"laptop","141":"laptop","142":"laptop","143":"laptop","144":"laptop","145":"laptop","146":"laptop","147":"laptop","148":"laptop","149":"laptop","150":"laptop","151":"laptop","152":"laptop","153":"laptop","154":"laptop","155":"laptop","156":"laptop","157":"laptop","158":"laptop","159":"laptop","160":"maze","161":"maze","162":"maze","163":"maze","164":"maze","165":"maze","166":"maze","167":"maze","168":"maze","169":"maze","170":"maze","171":"maze","172":"maze","173":"maze","174":"maze","175":"maze","176":"maze","177":"maze","178":"maze","179":"maze","180":"maze","181":"maze","182":"maze","183":"maze","184":"maze","185":"maze","186":"maze","187":"maze","188":"maze","189":"maze","190":"maze","191":"maze","192":"maze","193":"maze","194":"maze","195":"maze","196":"maze","197":"maze","198":"maze","199":"maze","200":"parking meter","201":"parking meter","202":"parking meter","203":"parking meter","204":"parking meter","205":"parking meter","206":"parking meter","207":"parking meter","208":"parking meter","209":"parking meter","210":"parking meter","211":"parking meter","212":"parking meter","213":"parking meter","214":"parking meter","215":"parking meter","216":"parking meter","217":"parking meter","218":"parking meter","219":"parking meter","220":"parking meter","221":"parking meter","222":"parking meter","223":"parking meter","224":"parking meter","225":"parking meter","226":"parking meter","227":"parking meter","228":"parking meter","229":"parking meter","230":"parking meter","231":"parking meter","232":"parking meter","233":"parking meter","234":"parking meter","235":"parking meter","236":"parking meter","237":"parking meter","238":"parking meter","239":"parking meter","240":"pizza","241":"pizza","242":"pizza","243":"pizza","244":"pizza","245":"pizza","246":"pizza","247":"pizza","248":"pizza","249":"pizza","250":"pizza","251":"pizza","252":"pizza","253":"pizza","254":"pizza","255":"pizza","256":"pizza","257":"pizza","258":"pizza","259":"pizza","260":"pizza","261":"pizza","262":"pizza","263":"pizza","264":"pizza","265":"pizza","266":"pizza","267":"pizza","268":"pizza","269":"pizza","270":"pizza","271":"pizza","272":"pizza","273":"pizza","274":"pizza","275":"pizza","276":"pizza","277":"pizza","278":"pizza","279":"pizza","280":"traffic light","281":"traffic light","282":"traffic light","283":"traffic light","284":"traffic light","285":"traffic light","286":"traffic light","287":"traffic light","288":"traffic light","289":"traffic light","290":"traffic light","291":"traffic light","292":"traffic light","293":"traffic light","294":"traffic light","295":"traffic light","296":"traffic light","297":"traffic light","298":"traffic light","299":"traffic light","300":"traffic light","301":"traffic light","302":"traffic light","303":"traffic light","304":"traffic light","305":"traffic light","306":"traffic light","307":"traffic light","308":"traffic light","309":"traffic light","310":"traffic light","311":"traffic light","312":"traffic light","313":"traffic light","314":"traffic light","315":"traffic light","316":"traffic light","317":"traffic light","318":"traffic light","319":"traffic light","320":"umbrella","321":"umbrella","322":"umbrella","323":"umbrella","324":"umbrella","325":"umbrella","326":"umbrella","327":"umbrella","328":"umbrella","329":"umbrella","330":"umbrella","331":"umbrella","332":"umbrella","333":"umbrella","334":"umbrella","335":"umbrella","336":"umbrella","337":"umbrella","338":"umbrella","339":"umbrella","340":"umbrella","341":"umbrella","342":"umbrella","343":"umbrella","344":"umbrella","345":"umbrella","346":"umbrella","347":"umbrella","348":"umbrella","349":"umbrella","350":"umbrella","351":"umbrella","352":"umbrella","353":"umbrella","354":"umbrella","355":"umbrella","356":"umbrella","357":"umbrella","358":"umbrella","359":"umbrella","360":"wall clock","361":"wall clock","362":"wall clock","363":"wall clock","364":"wall clock","365":"wall clock","366":"wall clock","367":"wall clock","368":"wall clock","369":"wall clock","370":"wall clock","371":"wall clock","372":"wall clock","373":"wall clock","374":"wall clock","375":"wall clock","376":"wall clock","377":"wall clock","378":"wall clock","379":"wall clock","380":"wall clock","381":"wall clock","382":"wall clock","383":"wall clock","384":"wall clock","385":"wall clock","386":"wall clock","387":"wall clock","388":"wall clock","389":"wall clock","390":"wall clock","391":"wall clock","392":"wall clock","393":"wall clock","394":"wall clock","395":"wall clock","396":"wall clock","397":"wall clock","398":"wall clock","399":"wall clock"},"i_label":{"0":409,"1":409,"2":409,"3":409,"4":409,"5":409,"6":409,"7":409,"8":409,"9":409,"10":409,"11":409,"12":409,"13":409,"14":409,"15":409,"16":409,"17":409,"18":409,"19":409,"20":409,"21":409,"22":409,"23":409,"24":409,"25":409,"26":409,"27":409,"28":409,"29":409,"30":409,"31":409,"32":409,"33":409,"34":409,"35":409,"36":409,"37":409,"38":409,"39":409,"40":487,"41":487,"42":487,"43":487,"44":487,"45":487,"46":487,"47":487,"48":487,"49":487,"50":487,"51":487,"52":487,"53":487,"54":487,"55":487,"56":487,"57":487,"58":487,"59":487,"60":487,"61":487,"62":487,"63":487,"64":487,"65":487,"66":487,"67":487,"68":487,"69":487,"70":487,"71":487,"72":487,"73":487,"74":487,"75":487,"76":487,"77":487,"78":487,"79":487,"80":530,"81":530,"82":530,"83":530,"84":530,"85":530,"86":530,"87":530,"88":530,"89":530,"90":530,"91":530,"92":530,"93":530,"94":530,"95":530,"96":530,"97":530,"98":530,"99":530,"100":530,"101":530,"102":530,"103":530,"104":530,"105":530,"106":530,"107":530,"108":530,"109":530,"110":530,"111":530,"112":530,"113":530,"114":530,"115":530,"116":530,"117":530,"118":530,"119":530,"120":620,"121":620,"122":620,"123":620,"124":620,"125":620,"126":620,"127":620,"128":620,"129":620,"130":620,"131":620,"132":620,"133":620,"134":620,"135":620,"136":620,"137":620,"138":620,"139":620,"140":620,"141":620,"142":620,"143":620,"144":620,"145":620,"146":620,"147":620,"148":620,"149":620,"150":620,"151":620,"152":620,"153":620,"154":620,"155":620,"156":620,"157":620,"158":620,"159":620,"160":646,"161":646,"162":646,"163":646,"164":646,"165":646,"166":646,"167":646,"168":646,"169":646,"170":646,"171":646,"172":646,"173":646,"174":646,"175":646,"176":646,"177":646,"178":646,"179":646,"180":646,"181":646,"182":646,"183":646,"184":646,"185":646,"186":646,"187":646,"188":646,"189":646,"190":646,"191":646,"192":646,"193":646,"194":646,"195":646,"196":646,"197":646,"198":646,"199":646,"200":704,"201":704,"202":704,"203":704,"204":704,"205":704,"206":704,"207":704,"208":704,"209":704,"210":704,"211":704,"212":704,"213":704,"214":704,"215":704,"216":704,"217":704,"218":704,"219":704,"220":704,"221":704,"222":704,"223":704,"224":704,"225":704,"226":704,"227":704,"228":704,"229":704,"230":704,"231":704,"232":704,"233":704,"234":704,"235":704,"236":704,"237":704,"238":704,"239":704,"240":963,"241":963,"242":963,"243":963,"244":963,"245":963,"246":963,"247":963,"248":963,"249":963,"250":963,"251":963,"252":963,"253":963,"254":963,"255":963,"256":963,"257":963,"258":963,"259":963,"260":963,"261":963,"262":963,"263":963,"264":963,"265":963,"266":963,"267":963,"268":963,"269":963,"270":963,"271":963,"272":963,"273":963,"274":963,"275":963,"276":963,"277":963,"278":963,"279":963,"280":920,"281":920,"282":920,"283":920,"284":920,"285":920,"286":920,"287":920,"288":920,"289":920,"290":920,"291":920,"292":920,"293":920,"294":920,"295":920,"296":920,"297":920,"298":920,"299":920,"300":920,"301":920,"302":920,"303":920,"304":920,"305":920,"306":920,"307":920,"308":920,"309":920,"310":920,"311":920,"312":920,"313":920,"314":920,"315":920,"316":920,"317":920,"318":920,"319":920,"320":879,"321":879,"322":879,"323":879,"324":879,"325":879,"326":879,"327":879,"328":879,"329":879,"330":879,"331":879,"332":879,"333":879,"334":879,"335":879,"336":879,"337":879,"338":879,"339":879,"340":879,"341":879,"342":879,"343":879,"344":879,"345":879,"346":879,"347":879,"348":879,"349":879,"350":879,"351":879,"352":879,"353":879,"354":879,"355":879,"356":879,"357":879,"358":879,"359":879,"360":892,"361":892,"362":892,"363":892,"364":892,"365":892,"366":892,"367":892,"368":892,"369":892,"370":892,"371":892,"372":892,"373":892,"374":892,"375":892,"376":892,"377":892,"378":892,"379":892,"380":892,"381":892,"382":892,"383":892,"384":892,"385":892,"386":892,"387":892,"388":892,"389":892,"390":892,"391":892,"392":892,"393":892,"394":892,"395":892,"396":892,"397":892,"398":892,"399":892},"i_image":{"0":0,"1":0,"2":0,"3":0,"4":1,"5":1,"6":1,"7":1,"8":2,"9":2,"10":2,"11":2,"12":3,"13":3,"14":3,"15":3,"16":4,"17":4,"18":4,"19":4,"20":5,"21":5,"22":5,"23":5,"24":6,"25":6,"26":6,"27":6,"28":7,"29":7,"30":7,"31":7,"32":8,"33":8,"34":8,"35":8,"36":9,"37":9,"38":9,"39":9,"40":10,"41":10,"42":10,"43":10,"44":11,"45":11,"46":11,"47":11,"48":12,"49":12,"50":12,"51":12,"52":13,"53":13,"54":13,"55":13,"56":14,"57":14,"58":14,"59":14,"60":15,"61":15,"62":15,"63":15,"64":16,"65":16,"66":16,"67":16,"68":17,"69":17,"70":17,"71":17,"72":18,"73":18,"74":18,"75":18,"76":19,"77":19,"78":19,"79":19,"80":20,"81":20,"82":20,"83":20,"84":21,"85":21,"86":21,"87":21,"88":22,"89":22,"90":22,"91":22,"92":23,"93":23,"94":23,"95":23,"96":24,"97":24,"98":24,"99":24,"100":25,"101":25,"102":25,"103":25,"104":26,"105":26,"106":26,"107":26,"108":27,"109":27,"110":27,"111":27,"112":28,"113":28,"114":28,"115":28,"116":29,"117":29,"118":29,"119":29,"120":30,"121":30,"122":30,"123":30,"124":31,"125":31,"126":31,"127":31,"128":32,"129":32,"130":32,"131":32,"132":33,"133":33,"134":33,"135":33,"136":34,"137":34,"138":34,"139":34,"140":35,"141":35,"142":35,"143":35,"144":36,"145":36,"146":36,"147":36,"148":37,"149":37,"150":37,"151":37,"152":38,"153":38,"154":38,"155":38,"156":39,"157":39,"158":39,"159":39,"160":40,"161":40,"162":40,"163":40,"164":41,"165":41,"166":41,"167":41,"168":42,"169":42,"170":42,"171":42,"172":43,"173":43,"174":43,"175":43,"176":44,"177":44,"178":44,"179":44,"180":45,"181":45,"182":45,"183":45,"184":46,"185":46,"186":46,"187":46,"188":47,"189":47,"190":47,"191":47,"192":48,"193":48,"194":48,"195":48,"196":49,"197":49,"198":49,"199":49,"200":50,"201":50,"202":50,"203":50,"204":51,"205":51,"206":51,"207":51,"208":52,"209":52,"210":52,"211":52,"212":53,"213":53,"214":53,"215":53,"216":54,"217":54,"218":54,"219":54,"220":55,"221":55,"222":55,"223":55,"224":56,"225":56,"226":56,"227":56,"228":57,"229":57,"230":57,"231":57,"232":58,"233":58,"234":58,"235":58,"236":59,"237":59,"238":59,"239":59,"240":60,"241":60,"242":60,"243":60,"244":61,"245":61,"246":61,"247":61,"248":62,"249":62,"250":62,"251":62,"252":63,"253":63,"254":63,"255":63,"256":64,"257":64,"258":64,"259":64,"260":65,"261":65,"262":65,"263":65,"264":66,"265":66,"266":66,"267":66,"268":67,"269":67,"270":67,"271":67,"272":68,"273":68,"274":68,"275":68,"276":69,"277":69,"278":69,"279":69,"280":70,"281":70,"282":70,"283":70,"284":71,"285":71,"286":71,"287":71,"288":72,"289":72,"290":72,"291":72,"292":73,"293":73,"294":73,"295":73,"296":74,"297":74,"298":74,"299":74,"300":75,"301":75,"302":75,"303":75,"304":76,"305":76,"306":76,"307":76,"308":77,"309":77,"310":77,"311":77,"312":78,"313":78,"314":78,"315":78,"316":79,"317":79,"318":79,"319":79,"320":80,"321":80,"322":80,"323":80,"324":81,"325":81,"326":81,"327":81,"328":82,"329":82,"330":82,"331":82,"332":83,"333":83,"334":83,"335":83,"336":84,"337":84,"338":84,"339":84,"340":85,"341":85,"342":85,"343":85,"344":86,"345":86,"346":86,"347":86,"348":87,"349":87,"350":87,"351":87,"352":88,"353":88,"354":88,"355":88,"356":89,"357":89,"358":89,"359":89,"360":90,"361":90,"362":90,"363":90,"364":91,"365":91,"366":91,"367":91,"368":92,"369":92,"370":92,"371":92,"372":93,"373":93,"374":93,"375":93,"376":94,"377":94,"378":94,"379":94,"380":95,"381":95,"382":95,"383":95,"384":96,"385":96,"386":96,"387":96,"388":97,"389":97,"390":97,"391":97,"392":98,"393":98,"394":98,"395":98,"396":99,"397":99,"398":99,"399":99},"filename":{"0":"data\/imagenet_classes_100\/analog clock\/115132966_f56ae9c94f.jpg","1":"data\/imagenet_classes_100\/analog clock\/115132966_f56ae9c94f.jpg","2":"data\/imagenet_classes_100\/analog clock\/115132966_f56ae9c94f.jpg","3":"data\/imagenet_classes_100\/analog clock\/115132966_f56ae9c94f.jpg","4":"data\/imagenet_classes_100\/analog clock\/1388545748_a3c28f8ffc.jpg","5":"data\/imagenet_classes_100\/analog clock\/1388545748_a3c28f8ffc.jpg","6":"data\/imagenet_classes_100\/analog clock\/1388545748_a3c28f8ffc.jpg","7":"data\/imagenet_classes_100\/analog clock\/1388545748_a3c28f8ffc.jpg","8":"data\/imagenet_classes_100\/analog clock\/2044469143_47990ff6ac.jpg","9":"data\/imagenet_classes_100\/analog clock\/2044469143_47990ff6ac.jpg","10":"data\/imagenet_classes_100\/analog clock\/2044469143_47990ff6ac.jpg","11":"data\/imagenet_classes_100\/analog clock\/2044469143_47990ff6ac.jpg","12":"data\/imagenet_classes_100\/analog clock\/272221207_34714fc3c1.jpg","13":"data\/imagenet_classes_100\/analog clock\/272221207_34714fc3c1.jpg","14":"data\/imagenet_classes_100\/analog clock\/272221207_34714fc3c1.jpg","15":"data\/imagenet_classes_100\/analog clock\/272221207_34714fc3c1.jpg","16":"data\/imagenet_classes_100\/analog clock\/2951149311_c0840a2e55.jpg","17":"data\/imagenet_classes_100\/analog clock\/2951149311_c0840a2e55.jpg","18":"data\/imagenet_classes_100\/analog clock\/2951149311_c0840a2e55.jpg","19":"data\/imagenet_classes_100\/analog clock\/2951149311_c0840a2e55.jpg","20":"data\/imagenet_classes_100\/analog clock\/308585525_d6a682779f.jpg","21":"data\/imagenet_classes_100\/analog clock\/308585525_d6a682779f.jpg","22":"data\/imagenet_classes_100\/analog clock\/308585525_d6a682779f.jpg","23":"data\/imagenet_classes_100\/analog clock\/308585525_d6a682779f.jpg","24":"data\/imagenet_classes_100\/analog clock\/377503851_08262a19db.jpg","25":"data\/imagenet_classes_100\/analog clock\/377503851_08262a19db.jpg","26":"data\/imagenet_classes_100\/analog clock\/377503851_08262a19db.jpg","27":"data\/imagenet_classes_100\/analog clock\/377503851_08262a19db.jpg","28":"data\/imagenet_classes_100\/analog clock\/535635256_7d5567010a.jpg","29":"data\/imagenet_classes_100\/analog clock\/535635256_7d5567010a.jpg","30":"data\/imagenet_classes_100\/analog clock\/535635256_7d5567010a.jpg","31":"data\/imagenet_classes_100\/analog clock\/535635256_7d5567010a.jpg","32":"data\/imagenet_classes_100\/analog clock\/7086775_d164ac95db.jpg","33":"data\/imagenet_classes_100\/analog clock\/7086775_d164ac95db.jpg","34":"data\/imagenet_classes_100\/analog clock\/7086775_d164ac95db.jpg","35":"data\/imagenet_classes_100\/analog clock\/7086775_d164ac95db.jpg","36":"data\/imagenet_classes_100\/analog clock\/759002761_c3224820d5.jpg","37":"data\/imagenet_classes_100\/analog clock\/759002761_c3224820d5.jpg","38":"data\/imagenet_classes_100\/analog clock\/759002761_c3224820d5.jpg","39":"data\/imagenet_classes_100\/analog clock\/759002761_c3224820d5.jpg","40":"data\/imagenet_classes_100\/cellular telephone\/123429226_53b56824bb.jpg","41":"data\/imagenet_classes_100\/cellular telephone\/123429226_53b56824bb.jpg","42":"data\/imagenet_classes_100\/cellular telephone\/123429226_53b56824bb.jpg","43":"data\/imagenet_classes_100\/cellular telephone\/123429226_53b56824bb.jpg","44":"data\/imagenet_classes_100\/cellular telephone\/187689499_97f5e71935.jpg","45":"data\/imagenet_classes_100\/cellular telephone\/187689499_97f5e71935.jpg","46":"data\/imagenet_classes_100\/cellular telephone\/187689499_97f5e71935.jpg","47":"data\/imagenet_classes_100\/cellular telephone\/187689499_97f5e71935.jpg","48":"data\/imagenet_classes_100\/cellular telephone\/218188661_35ab70df72.jpg","49":"data\/imagenet_classes_100\/cellular telephone\/218188661_35ab70df72.jpg","50":"data\/imagenet_classes_100\/cellular telephone\/218188661_35ab70df72.jpg","51":"data\/imagenet_classes_100\/cellular telephone\/218188661_35ab70df72.jpg","52":"data\/imagenet_classes_100\/cellular telephone\/2377756276_4c3623c353.jpg","53":"data\/imagenet_classes_100\/cellular telephone\/2377756276_4c3623c353.jpg","54":"data\/imagenet_classes_100\/cellular telephone\/2377756276_4c3623c353.jpg","55":"data\/imagenet_classes_100\/cellular telephone\/2377756276_4c3623c353.jpg","56":"data\/imagenet_classes_100\/cellular telephone\/2496609968_2a993b0458.jpg","57":"data\/imagenet_classes_100\/cellular telephone\/2496609968_2a993b0458.jpg","58":"data\/imagenet_classes_100\/cellular telephone\/2496609968_2a993b0458.jpg","59":"data\/imagenet_classes_100\/cellular telephone\/2496609968_2a993b0458.jpg","60":"data\/imagenet_classes_100\/cellular telephone\/2595357619_7674575e62.jpg","61":"data\/imagenet_classes_100\/cellular telephone\/2595357619_7674575e62.jpg","62":"data\/imagenet_classes_100\/cellular telephone\/2595357619_7674575e62.jpg","63":"data\/imagenet_classes_100\/cellular telephone\/2595357619_7674575e62.jpg","64":"data\/imagenet_classes_100\/cellular telephone\/2825095151_f114959525.jpg","65":"data\/imagenet_classes_100\/cellular telephone\/2825095151_f114959525.jpg","66":"data\/imagenet_classes_100\/cellular telephone\/2825095151_f114959525.jpg","67":"data\/imagenet_classes_100\/cellular telephone\/2825095151_f114959525.jpg","68":"data\/imagenet_classes_100\/cellular telephone\/446448280_54f7fd97d6.jpg","69":"data\/imagenet_classes_100\/cellular telephone\/446448280_54f7fd97d6.jpg","70":"data\/imagenet_classes_100\/cellular telephone\/446448280_54f7fd97d6.jpg","71":"data\/imagenet_classes_100\/cellular telephone\/446448280_54f7fd97d6.jpg","72":"data\/imagenet_classes_100\/cellular telephone\/56547747_ea2fb580be.jpg","73":"data\/imagenet_classes_100\/cellular telephone\/56547747_ea2fb580be.jpg","74":"data\/imagenet_classes_100\/cellular telephone\/56547747_ea2fb580be.jpg","75":"data\/imagenet_classes_100\/cellular telephone\/56547747_ea2fb580be.jpg","76":"data\/imagenet_classes_100\/cellular telephone\/856683107_b64988031e.jpg","77":"data\/imagenet_classes_100\/cellular telephone\/856683107_b64988031e.jpg","78":"data\/imagenet_classes_100\/cellular telephone\/856683107_b64988031e.jpg","79":"data\/imagenet_classes_100\/cellular telephone\/856683107_b64988031e.jpg","80":"data\/imagenet_classes_100\/digital clock\/1438545882_6a5b5e3bb0.jpg","81":"data\/imagenet_classes_100\/digital clock\/1438545882_6a5b5e3bb0.jpg","82":"data\/imagenet_classes_100\/digital clock\/1438545882_6a5b5e3bb0.jpg","83":"data\/imagenet_classes_100\/digital clock\/1438545882_6a5b5e3bb0.jpg","84":"data\/imagenet_classes_100\/digital clock\/159599131_08aaa57a47.jpg","85":"data\/imagenet_classes_100\/digital clock\/159599131_08aaa57a47.jpg","86":"data\/imagenet_classes_100\/digital clock\/159599131_08aaa57a47.jpg","87":"data\/imagenet_classes_100\/digital clock\/159599131_08aaa57a47.jpg","88":"data\/imagenet_classes_100\/digital clock\/2102629241_ffbb3e571c.jpg","89":"data\/imagenet_classes_100\/digital clock\/2102629241_ffbb3e571c.jpg","90":"data\/imagenet_classes_100\/digital clock\/2102629241_ffbb3e571c.jpg","91":"data\/imagenet_classes_100\/digital clock\/2102629241_ffbb3e571c.jpg","92":"data\/imagenet_classes_100\/digital clock\/2219131237_dd4df716b9.jpg","93":"data\/imagenet_classes_100\/digital clock\/2219131237_dd4df716b9.jpg","94":"data\/imagenet_classes_100\/digital clock\/2219131237_dd4df716b9.jpg","95":"data\/imagenet_classes_100\/digital clock\/2219131237_dd4df716b9.jpg","96":"data\/imagenet_classes_100\/digital clock\/2342394852_bf8d42027d.jpg","97":"data\/imagenet_classes_100\/digital clock\/2342394852_bf8d42027d.jpg","98":"data\/imagenet_classes_100\/digital clock\/2342394852_bf8d42027d.jpg","99":"data\/imagenet_classes_100\/digital clock\/2342394852_bf8d42027d.jpg","100":"data\/imagenet_classes_100\/digital clock\/273628896_e18bd4d528.jpg","101":"data\/imagenet_classes_100\/digital clock\/273628896_e18bd4d528.jpg","102":"data\/imagenet_classes_100\/digital clock\/273628896_e18bd4d528.jpg","103":"data\/imagenet_classes_100\/digital clock\/273628896_e18bd4d528.jpg","104":"data\/imagenet_classes_100\/digital clock\/2928882256_6bdf662090.jpg","105":"data\/imagenet_classes_100\/digital clock\/2928882256_6bdf662090.jpg","106":"data\/imagenet_classes_100\/digital clock\/2928882256_6bdf662090.jpg","107":"data\/imagenet_classes_100\/digital clock\/2928882256_6bdf662090.jpg","108":"data\/imagenet_classes_100\/digital clock\/346271479_b06b15f730.jpg","109":"data\/imagenet_classes_100\/digital clock\/346271479_b06b15f730.jpg","110":"data\/imagenet_classes_100\/digital clock\/346271479_b06b15f730.jpg","111":"data\/imagenet_classes_100\/digital clock\/346271479_b06b15f730.jpg","112":"data\/imagenet_classes_100\/digital clock\/491395274_5c02b8bb75.jpg","113":"data\/imagenet_classes_100\/digital clock\/491395274_5c02b8bb75.jpg","114":"data\/imagenet_classes_100\/digital clock\/491395274_5c02b8bb75.jpg","115":"data\/imagenet_classes_100\/digital clock\/491395274_5c02b8bb75.jpg","116":"data\/imagenet_classes_100\/digital clock\/49363681_48797513f2.jpg","117":"data\/imagenet_classes_100\/digital clock\/49363681_48797513f2.jpg","118":"data\/imagenet_classes_100\/digital clock\/49363681_48797513f2.jpg","119":"data\/imagenet_classes_100\/digital clock\/49363681_48797513f2.jpg","120":"data\/imagenet_classes_100\/laptop\/1156362438_912b8810dd.jpg","121":"data\/imagenet_classes_100\/laptop\/1156362438_912b8810dd.jpg","122":"data\/imagenet_classes_100\/laptop\/1156362438_912b8810dd.jpg","123":"data\/imagenet_classes_100\/laptop\/1156362438_912b8810dd.jpg","124":"data\/imagenet_classes_100\/laptop\/123208237_7d0b5ad733.jpg","125":"data\/imagenet_classes_100\/laptop\/123208237_7d0b5ad733.jpg","126":"data\/imagenet_classes_100\/laptop\/123208237_7d0b5ad733.jpg","127":"data\/imagenet_classes_100\/laptop\/123208237_7d0b5ad733.jpg","128":"data\/imagenet_classes_100\/laptop\/2058475786_d4eedce568.jpg","129":"data\/imagenet_classes_100\/laptop\/2058475786_d4eedce568.jpg","130":"data\/imagenet_classes_100\/laptop\/2058475786_d4eedce568.jpg","131":"data\/imagenet_classes_100\/laptop\/2058475786_d4eedce568.jpg","132":"data\/imagenet_classes_100\/laptop\/2228134763_227e8b311c.jpg","133":"data\/imagenet_classes_100\/laptop\/2228134763_227e8b311c.jpg","134":"data\/imagenet_classes_100\/laptop\/2228134763_227e8b311c.jpg","135":"data\/imagenet_classes_100\/laptop\/2228134763_227e8b311c.jpg","136":"data\/imagenet_classes_100\/laptop\/262680262_6f8aa6a617.jpg","137":"data\/imagenet_classes_100\/laptop\/262680262_6f8aa6a617.jpg","138":"data\/imagenet_classes_100\/laptop\/262680262_6f8aa6a617.jpg","139":"data\/imagenet_classes_100\/laptop\/262680262_6f8aa6a617.jpg","140":"data\/imagenet_classes_100\/laptop\/359870165_39c7977f73.jpg","141":"data\/imagenet_classes_100\/laptop\/359870165_39c7977f73.jpg","142":"data\/imagenet_classes_100\/laptop\/359870165_39c7977f73.jpg","143":"data\/imagenet_classes_100\/laptop\/359870165_39c7977f73.jpg","144":"data\/imagenet_classes_100\/laptop\/498645624_eeabe1253b.jpg","145":"data\/imagenet_classes_100\/laptop\/498645624_eeabe1253b.jpg","146":"data\/imagenet_classes_100\/laptop\/498645624_eeabe1253b.jpg","147":"data\/imagenet_classes_100\/laptop\/498645624_eeabe1253b.jpg","148":"data\/imagenet_classes_100\/laptop\/82236949_693a4f4b58.jpg","149":"data\/imagenet_classes_100\/laptop\/82236949_693a4f4b58.jpg","150":"data\/imagenet_classes_100\/laptop\/82236949_693a4f4b58.jpg","151":"data\/imagenet_classes_100\/laptop\/82236949_693a4f4b58.jpg","152":"data\/imagenet_classes_100\/laptop\/86347611_3eed034acd.jpg","153":"data\/imagenet_classes_100\/laptop\/86347611_3eed034acd.jpg","154":"data\/imagenet_classes_100\/laptop\/86347611_3eed034acd.jpg","155":"data\/imagenet_classes_100\/laptop\/86347611_3eed034acd.jpg","156":"data\/imagenet_classes_100\/laptop\/943160343_7c5be7a3da.jpg","157":"data\/imagenet_classes_100\/laptop\/943160343_7c5be7a3da.jpg","158":"data\/imagenet_classes_100\/laptop\/943160343_7c5be7a3da.jpg","159":"data\/imagenet_classes_100\/laptop\/943160343_7c5be7a3da.jpg","160":"data\/imagenet_classes_100\/maze\/106956687_743a6bf759.jpg","161":"data\/imagenet_classes_100\/maze\/106956687_743a6bf759.jpg","162":"data\/imagenet_classes_100\/maze\/106956687_743a6bf759.jpg","163":"data\/imagenet_classes_100\/maze\/106956687_743a6bf759.jpg","164":"data\/imagenet_classes_100\/maze\/1462808184_219039a50c.jpg","165":"data\/imagenet_classes_100\/maze\/1462808184_219039a50c.jpg","166":"data\/imagenet_classes_100\/maze\/1462808184_219039a50c.jpg","167":"data\/imagenet_classes_100\/maze\/1462808184_219039a50c.jpg","168":"data\/imagenet_classes_100\/maze\/2191215506_4b90ac5911.jpg","169":"data\/imagenet_classes_100\/maze\/2191215506_4b90ac5911.jpg","170":"data\/imagenet_classes_100\/maze\/2191215506_4b90ac5911.jpg","171":"data\/imagenet_classes_100\/maze\/2191215506_4b90ac5911.jpg","172":"data\/imagenet_classes_100\/maze\/2485331808_f8584cde0f.jpg","173":"data\/imagenet_classes_100\/maze\/2485331808_f8584cde0f.jpg","174":"data\/imagenet_classes_100\/maze\/2485331808_f8584cde0f.jpg","175":"data\/imagenet_classes_100\/maze\/2485331808_f8584cde0f.jpg","176":"data\/imagenet_classes_100\/maze\/2646269750_22bb293c81.jpg","177":"data\/imagenet_classes_100\/maze\/2646269750_22bb293c81.jpg","178":"data\/imagenet_classes_100\/maze\/2646269750_22bb293c81.jpg","179":"data\/imagenet_classes_100\/maze\/2646269750_22bb293c81.jpg","180":"data\/imagenet_classes_100\/maze\/2926126567_cc7630c1a9.jpg","181":"data\/imagenet_classes_100\/maze\/2926126567_cc7630c1a9.jpg","182":"data\/imagenet_classes_100\/maze\/2926126567_cc7630c1a9.jpg","183":"data\/imagenet_classes_100\/maze\/2926126567_cc7630c1a9.jpg","184":"data\/imagenet_classes_100\/maze\/2997109750_e8455a9d94.jpg","185":"data\/imagenet_classes_100\/maze\/2997109750_e8455a9d94.jpg","186":"data\/imagenet_classes_100\/maze\/2997109750_e8455a9d94.jpg","187":"data\/imagenet_classes_100\/maze\/2997109750_e8455a9d94.jpg","188":"data\/imagenet_classes_100\/maze\/3007957179_84925c057b.jpg","189":"data\/imagenet_classes_100\/maze\/3007957179_84925c057b.jpg","190":"data\/imagenet_classes_100\/maze\/3007957179_84925c057b.jpg","191":"data\/imagenet_classes_100\/maze\/3007957179_84925c057b.jpg","192":"data\/imagenet_classes_100\/maze\/3173555944_1d24864959.jpg","193":"data\/imagenet_classes_100\/maze\/3173555944_1d24864959.jpg","194":"data\/imagenet_classes_100\/maze\/3173555944_1d24864959.jpg","195":"data\/imagenet_classes_100\/maze\/3173555944_1d24864959.jpg","196":"data\/imagenet_classes_100\/maze\/337559279_9bd8867b59.jpg","197":"data\/imagenet_classes_100\/maze\/337559279_9bd8867b59.jpg","198":"data\/imagenet_classes_100\/maze\/337559279_9bd8867b59.jpg","199":"data\/imagenet_classes_100\/maze\/337559279_9bd8867b59.jpg","200":"data\/imagenet_classes_100\/parking meter\/228863326_18f355d852.jpg","201":"data\/imagenet_classes_100\/parking meter\/228863326_18f355d852.jpg","202":"data\/imagenet_classes_100\/parking meter\/228863326_18f355d852.jpg","203":"data\/imagenet_classes_100\/parking meter\/228863326_18f355d852.jpg","204":"data\/imagenet_classes_100\/parking meter\/231441359_4421af827c.jpg","205":"data\/imagenet_classes_100\/parking meter\/231441359_4421af827c.jpg","206":"data\/imagenet_classes_100\/parking meter\/231441359_4421af827c.jpg","207":"data\/imagenet_classes_100\/parking meter\/231441359_4421af827c.jpg","208":"data\/imagenet_classes_100\/parking meter\/2336669144_70c23f1f1a.jpg","209":"data\/imagenet_classes_100\/parking meter\/2336669144_70c23f1f1a.jpg","210":"data\/imagenet_classes_100\/parking meter\/2336669144_70c23f1f1a.jpg","211":"data\/imagenet_classes_100\/parking meter\/2336669144_70c23f1f1a.jpg","212":"data\/imagenet_classes_100\/parking meter\/243243015_fe354f9703.jpg","213":"data\/imagenet_classes_100\/parking meter\/243243015_fe354f9703.jpg","214":"data\/imagenet_classes_100\/parking meter\/243243015_fe354f9703.jpg","215":"data\/imagenet_classes_100\/parking meter\/243243015_fe354f9703.jpg","216":"data\/imagenet_classes_100\/parking meter\/2462245406_d9ff2ae681.jpg","217":"data\/imagenet_classes_100\/parking meter\/2462245406_d9ff2ae681.jpg","218":"data\/imagenet_classes_100\/parking meter\/2462245406_d9ff2ae681.jpg","219":"data\/imagenet_classes_100\/parking meter\/2462245406_d9ff2ae681.jpg","220":"data\/imagenet_classes_100\/parking meter\/2462961097_12882c8bf3.jpg","221":"data\/imagenet_classes_100\/parking meter\/2462961097_12882c8bf3.jpg","222":"data\/imagenet_classes_100\/parking meter\/2462961097_12882c8bf3.jpg","223":"data\/imagenet_classes_100\/parking meter\/2462961097_12882c8bf3.jpg","224":"data\/imagenet_classes_100\/parking meter\/2760097077_85c9e1f3f4.jpg","225":"data\/imagenet_classes_100\/parking meter\/2760097077_85c9e1f3f4.jpg","226":"data\/imagenet_classes_100\/parking meter\/2760097077_85c9e1f3f4.jpg","227":"data\/imagenet_classes_100\/parking meter\/2760097077_85c9e1f3f4.jpg","228":"data\/imagenet_classes_100\/parking meter\/2833459913_f37b46b13e.jpg","229":"data\/imagenet_classes_100\/parking meter\/2833459913_f37b46b13e.jpg","230":"data\/imagenet_classes_100\/parking meter\/2833459913_f37b46b13e.jpg","231":"data\/imagenet_classes_100\/parking meter\/2833459913_f37b46b13e.jpg","232":"data\/imagenet_classes_100\/parking meter\/35198817_8132d940cb.jpg","233":"data\/imagenet_classes_100\/parking meter\/35198817_8132d940cb.jpg","234":"data\/imagenet_classes_100\/parking meter\/35198817_8132d940cb.jpg","235":"data\/imagenet_classes_100\/parking meter\/35198817_8132d940cb.jpg","236":"data\/imagenet_classes_100\/parking meter\/91840392_acd787f63e.jpg","237":"data\/imagenet_classes_100\/parking meter\/91840392_acd787f63e.jpg","238":"data\/imagenet_classes_100\/parking meter\/91840392_acd787f63e.jpg","239":"data\/imagenet_classes_100\/parking meter\/91840392_acd787f63e.jpg","240":"data\/imagenet_classes_100\/pizza\/146639031_31723b0ff7.jpg","241":"data\/imagenet_classes_100\/pizza\/146639031_31723b0ff7.jpg","242":"data\/imagenet_classes_100\/pizza\/146639031_31723b0ff7.jpg","243":"data\/imagenet_classes_100\/pizza\/146639031_31723b0ff7.jpg","244":"data\/imagenet_classes_100\/pizza\/152996006_66ff40702c.jpg","245":"data\/imagenet_classes_100\/pizza\/152996006_66ff40702c.jpg","246":"data\/imagenet_classes_100\/pizza\/152996006_66ff40702c.jpg","247":"data\/imagenet_classes_100\/pizza\/152996006_66ff40702c.jpg","248":"data\/imagenet_classes_100\/pizza\/227675530_b97ea8210f.jpg","249":"data\/imagenet_classes_100\/pizza\/227675530_b97ea8210f.jpg","250":"data\/imagenet_classes_100\/pizza\/227675530_b97ea8210f.jpg","251":"data\/imagenet_classes_100\/pizza\/227675530_b97ea8210f.jpg","252":"data\/imagenet_classes_100\/pizza\/2282810258_b2dc39a560.jpg","253":"data\/imagenet_classes_100\/pizza\/2282810258_b2dc39a560.jpg","254":"data\/imagenet_classes_100\/pizza\/2282810258_b2dc39a560.jpg","255":"data\/imagenet_classes_100\/pizza\/2282810258_b2dc39a560.jpg","256":"data\/imagenet_classes_100\/pizza\/2460137196_cfbe933ee2.jpg","257":"data\/imagenet_classes_100\/pizza\/2460137196_cfbe933ee2.jpg","258":"data\/imagenet_classes_100\/pizza\/2460137196_cfbe933ee2.jpg","259":"data\/imagenet_classes_100\/pizza\/2460137196_cfbe933ee2.jpg","260":"data\/imagenet_classes_100\/pizza\/2714395801_d31ce40dab.jpg","261":"data\/imagenet_classes_100\/pizza\/2714395801_d31ce40dab.jpg","262":"data\/imagenet_classes_100\/pizza\/2714395801_d31ce40dab.jpg","263":"data\/imagenet_classes_100\/pizza\/2714395801_d31ce40dab.jpg","264":"data\/imagenet_classes_100\/pizza\/2880231196_f41bd9732e.jpg","265":"data\/imagenet_classes_100\/pizza\/2880231196_f41bd9732e.jpg","266":"data\/imagenet_classes_100\/pizza\/2880231196_f41bd9732e.jpg","267":"data\/imagenet_classes_100\/pizza\/2880231196_f41bd9732e.jpg","268":"data\/imagenet_classes_100\/pizza\/3182498543_8a306e6aeb.jpg","269":"data\/imagenet_classes_100\/pizza\/3182498543_8a306e6aeb.jpg","270":"data\/imagenet_classes_100\/pizza\/3182498543_8a306e6aeb.jpg","271":"data\/imagenet_classes_100\/pizza\/3182498543_8a306e6aeb.jpg","272":"data\/imagenet_classes_100\/pizza\/3197291062_30a65d13a1.jpg","273":"data\/imagenet_classes_100\/pizza\/3197291062_30a65d13a1.jpg","274":"data\/imagenet_classes_100\/pizza\/3197291062_30a65d13a1.jpg","275":"data\/imagenet_classes_100\/pizza\/3197291062_30a65d13a1.jpg","276":"data\/imagenet_classes_100\/pizza\/3994490118_4ae4cf3f8e.jpg","277":"data\/imagenet_classes_100\/pizza\/3994490118_4ae4cf3f8e.jpg","278":"data\/imagenet_classes_100\/pizza\/3994490118_4ae4cf3f8e.jpg","279":"data\/imagenet_classes_100\/pizza\/3994490118_4ae4cf3f8e.jpg","280":"data\/imagenet_classes_100\/traffic light\/2007120982_df4775a58d.jpg","281":"data\/imagenet_classes_100\/traffic light\/2007120982_df4775a58d.jpg","282":"data\/imagenet_classes_100\/traffic light\/2007120982_df4775a58d.jpg","283":"data\/imagenet_classes_100\/traffic light\/2007120982_df4775a58d.jpg","284":"data\/imagenet_classes_100\/traffic light\/2539294737_78e28f148a.jpg","285":"data\/imagenet_classes_100\/traffic light\/2539294737_78e28f148a.jpg","286":"data\/imagenet_classes_100\/traffic light\/2539294737_78e28f148a.jpg","287":"data\/imagenet_classes_100\/traffic light\/2539294737_78e28f148a.jpg","288":"data\/imagenet_classes_100\/traffic light\/2643079656_8b13b1df78.jpg","289":"data\/imagenet_classes_100\/traffic light\/2643079656_8b13b1df78.jpg","290":"data\/imagenet_classes_100\/traffic light\/2643079656_8b13b1df78.jpg","291":"data\/imagenet_classes_100\/traffic light\/2643079656_8b13b1df78.jpg","292":"data\/imagenet_classes_100\/traffic light\/2845111952_936e4a560c.jpg","293":"data\/imagenet_classes_100\/traffic light\/2845111952_936e4a560c.jpg","294":"data\/imagenet_classes_100\/traffic light\/2845111952_936e4a560c.jpg","295":"data\/imagenet_classes_100\/traffic light\/2845111952_936e4a560c.jpg","296":"data\/imagenet_classes_100\/traffic light\/3128521233_4c0c63757d.jpg","297":"data\/imagenet_classes_100\/traffic light\/3128521233_4c0c63757d.jpg","298":"data\/imagenet_classes_100\/traffic light\/3128521233_4c0c63757d.jpg","299":"data\/imagenet_classes_100\/traffic light\/3128521233_4c0c63757d.jpg","300":"data\/imagenet_classes_100\/traffic light\/3137561824_3599ed214d.jpg","301":"data\/imagenet_classes_100\/traffic light\/3137561824_3599ed214d.jpg","302":"data\/imagenet_classes_100\/traffic light\/3137561824_3599ed214d.jpg","303":"data\/imagenet_classes_100\/traffic light\/3137561824_3599ed214d.jpg","304":"data\/imagenet_classes_100\/traffic light\/3454247859_39c67c358a.jpg","305":"data\/imagenet_classes_100\/traffic light\/3454247859_39c67c358a.jpg","306":"data\/imagenet_classes_100\/traffic light\/3454247859_39c67c358a.jpg","307":"data\/imagenet_classes_100\/traffic light\/3454247859_39c67c358a.jpg","308":"data\/imagenet_classes_100\/traffic light\/3499782449_bed9cb1285.jpg","309":"data\/imagenet_classes_100\/traffic light\/3499782449_bed9cb1285.jpg","310":"data\/imagenet_classes_100\/traffic light\/3499782449_bed9cb1285.jpg","311":"data\/imagenet_classes_100\/traffic light\/3499782449_bed9cb1285.jpg","312":"data\/imagenet_classes_100\/traffic light\/3579767378_306454239b.jpg","313":"data\/imagenet_classes_100\/traffic light\/3579767378_306454239b.jpg","314":"data\/imagenet_classes_100\/traffic light\/3579767378_306454239b.jpg","315":"data\/imagenet_classes_100\/traffic light\/3579767378_306454239b.jpg","316":"data\/imagenet_classes_100\/traffic light\/53031772_8878195a62.jpg","317":"data\/imagenet_classes_100\/traffic light\/53031772_8878195a62.jpg","318":"data\/imagenet_classes_100\/traffic light\/53031772_8878195a62.jpg","319":"data\/imagenet_classes_100\/traffic light\/53031772_8878195a62.jpg","320":"data\/imagenet_classes_100\/umbrella\/103738489_76feb229e9.jpg","321":"data\/imagenet_classes_100\/umbrella\/103738489_76feb229e9.jpg","322":"data\/imagenet_classes_100\/umbrella\/103738489_76feb229e9.jpg","323":"data\/imagenet_classes_100\/umbrella\/103738489_76feb229e9.jpg","324":"data\/imagenet_classes_100\/umbrella\/116668949_795eb733ba.jpg","325":"data\/imagenet_classes_100\/umbrella\/116668949_795eb733ba.jpg","326":"data\/imagenet_classes_100\/umbrella\/116668949_795eb733ba.jpg","327":"data\/imagenet_classes_100\/umbrella\/116668949_795eb733ba.jpg","328":"data\/imagenet_classes_100\/umbrella\/1400852844_075f9bdb48.jpg","329":"data\/imagenet_classes_100\/umbrella\/1400852844_075f9bdb48.jpg","330":"data\/imagenet_classes_100\/umbrella\/1400852844_075f9bdb48.jpg","331":"data\/imagenet_classes_100\/umbrella\/1400852844_075f9bdb48.jpg","332":"data\/imagenet_classes_100\/umbrella\/1450607638_e4ea8264dc.jpg","333":"data\/imagenet_classes_100\/umbrella\/1450607638_e4ea8264dc.jpg","334":"data\/imagenet_classes_100\/umbrella\/1450607638_e4ea8264dc.jpg","335":"data\/imagenet_classes_100\/umbrella\/1450607638_e4ea8264dc.jpg","336":"data\/imagenet_classes_100\/umbrella\/160337391_ef50d06a5a.jpg","337":"data\/imagenet_classes_100\/umbrella\/160337391_ef50d06a5a.jpg","338":"data\/imagenet_classes_100\/umbrella\/160337391_ef50d06a5a.jpg","339":"data\/imagenet_classes_100\/umbrella\/160337391_ef50d06a5a.jpg","340":"data\/imagenet_classes_100\/umbrella\/216962004_1c3f36391b.jpg","341":"data\/imagenet_classes_100\/umbrella\/216962004_1c3f36391b.jpg","342":"data\/imagenet_classes_100\/umbrella\/216962004_1c3f36391b.jpg","343":"data\/imagenet_classes_100\/umbrella\/216962004_1c3f36391b.jpg","344":"data\/imagenet_classes_100\/umbrella\/2235577407_fe48860061.jpg","345":"data\/imagenet_classes_100\/umbrella\/2235577407_fe48860061.jpg","346":"data\/imagenet_classes_100\/umbrella\/2235577407_fe48860061.jpg","347":"data\/imagenet_classes_100\/umbrella\/2235577407_fe48860061.jpg","348":"data\/imagenet_classes_100\/umbrella\/253228064_e164351c01.jpg","349":"data\/imagenet_classes_100\/umbrella\/253228064_e164351c01.jpg","350":"data\/imagenet_classes_100\/umbrella\/253228064_e164351c01.jpg","351":"data\/imagenet_classes_100\/umbrella\/253228064_e164351c01.jpg","352":"data\/imagenet_classes_100\/umbrella\/57237837_4e316a355c.jpg","353":"data\/imagenet_classes_100\/umbrella\/57237837_4e316a355c.jpg","354":"data\/imagenet_classes_100\/umbrella\/57237837_4e316a355c.jpg","355":"data\/imagenet_classes_100\/umbrella\/57237837_4e316a355c.jpg","356":"data\/imagenet_classes_100\/umbrella\/591569058_d2c166a46e.jpg","357":"data\/imagenet_classes_100\/umbrella\/591569058_d2c166a46e.jpg","358":"data\/imagenet_classes_100\/umbrella\/591569058_d2c166a46e.jpg","359":"data\/imagenet_classes_100\/umbrella\/591569058_d2c166a46e.jpg","360":"data\/imagenet_classes_100\/wall clock\/10741231_caa73ba780.jpg","361":"data\/imagenet_classes_100\/wall clock\/10741231_caa73ba780.jpg","362":"data\/imagenet_classes_100\/wall clock\/10741231_caa73ba780.jpg","363":"data\/imagenet_classes_100\/wall clock\/10741231_caa73ba780.jpg","364":"data\/imagenet_classes_100\/wall clock\/1498060929_282eaa63bd.jpg","365":"data\/imagenet_classes_100\/wall clock\/1498060929_282eaa63bd.jpg","366":"data\/imagenet_classes_100\/wall clock\/1498060929_282eaa63bd.jpg","367":"data\/imagenet_classes_100\/wall clock\/1498060929_282eaa63bd.jpg","368":"data\/imagenet_classes_100\/wall clock\/2122543516_5e7d35032a.jpg","369":"data\/imagenet_classes_100\/wall clock\/2122543516_5e7d35032a.jpg","370":"data\/imagenet_classes_100\/wall clock\/2122543516_5e7d35032a.jpg","371":"data\/imagenet_classes_100\/wall clock\/2122543516_5e7d35032a.jpg","372":"data\/imagenet_classes_100\/wall clock\/2152222253_0fdafcfe01.jpg","373":"data\/imagenet_classes_100\/wall clock\/2152222253_0fdafcfe01.jpg","374":"data\/imagenet_classes_100\/wall clock\/2152222253_0fdafcfe01.jpg","375":"data\/imagenet_classes_100\/wall clock\/2152222253_0fdafcfe01.jpg","376":"data\/imagenet_classes_100\/wall clock\/2351524582_ff38d67393.jpg","377":"data\/imagenet_classes_100\/wall clock\/2351524582_ff38d67393.jpg","378":"data\/imagenet_classes_100\/wall clock\/2351524582_ff38d67393.jpg","379":"data\/imagenet_classes_100\/wall clock\/2351524582_ff38d67393.jpg","380":"data\/imagenet_classes_100\/wall clock\/2419372343_1b78272e2c.jpg","381":"data\/imagenet_classes_100\/wall clock\/2419372343_1b78272e2c.jpg","382":"data\/imagenet_classes_100\/wall clock\/2419372343_1b78272e2c.jpg","383":"data\/imagenet_classes_100\/wall clock\/2419372343_1b78272e2c.jpg","384":"data\/imagenet_classes_100\/wall clock\/2828380947_1400cdf4d9.jpg","385":"data\/imagenet_classes_100\/wall clock\/2828380947_1400cdf4d9.jpg","386":"data\/imagenet_classes_100\/wall clock\/2828380947_1400cdf4d9.jpg","387":"data\/imagenet_classes_100\/wall clock\/2828380947_1400cdf4d9.jpg","388":"data\/imagenet_classes_100\/wall clock\/2958420549_8c2184b935.jpg","389":"data\/imagenet_classes_100\/wall clock\/2958420549_8c2184b935.jpg","390":"data\/imagenet_classes_100\/wall clock\/2958420549_8c2184b935.jpg","391":"data\/imagenet_classes_100\/wall clock\/2958420549_8c2184b935.jpg","392":"data\/imagenet_classes_100\/wall clock\/309257032_1207dfd5b1.jpg","393":"data\/imagenet_classes_100\/wall clock\/309257032_1207dfd5b1.jpg","394":"data\/imagenet_classes_100\/wall clock\/309257032_1207dfd5b1.jpg","395":"data\/imagenet_classes_100\/wall clock\/309257032_1207dfd5b1.jpg","396":"data\/imagenet_classes_100\/wall clock\/795660853_34106c47bb.jpg","397":"data\/imagenet_classes_100\/wall clock\/795660853_34106c47bb.jpg","398":"data\/imagenet_classes_100\/wall clock\/795660853_34106c47bb.jpg","399":"data\/imagenet_classes_100\/wall clock\/795660853_34106c47bb.jpg"},"device":{"0":"cuda:0","1":"cuda:0","2":"cuda:0","3":"cuda:0","4":"cuda:0","5":"cuda:0","6":"cuda:0","7":"cuda:0","8":"cuda:0","9":"cuda:0","10":"cuda:0","11":"cuda:0","12":"cuda:0","13":"cuda:0","14":"cuda:0","15":"cuda:0","16":"cuda:0","17":"cuda:0","18":"cuda:0","19":"cuda:0","20":"cuda:0","21":"cuda:0","22":"cuda:0","23":"cuda:0","24":"cuda:0","25":"cuda:0","26":"cuda:0","27":"cuda:0","28":"cuda:0","29":"cuda:0","30":"cuda:0","31":"cuda:0","32":"cuda:0","33":"cuda:0","34":"cuda:0","35":"cuda:0","36":"cuda:0","37":"cuda:0","38":"cuda:0","39":"cuda:0","40":"cuda:0","41":"cuda:0","42":"cuda:0","43":"cuda:0","44":"cuda:0","45":"cuda:0","46":"cuda:0","47":"cuda:0","48":"cuda:0","49":"cuda:0","50":"cuda:0","51":"cuda:0","52":"cuda:0","53":"cuda:0","54":"cuda:0","55":"cuda:0","56":"cuda:0","57":"cuda:0","58":"cuda:0","59":"cuda:0","60":"cuda:0","61":"cuda:0","62":"cuda:0","63":"cuda:0","64":"cuda:0","65":"cuda:0","66":"cuda:0","67":"cuda:0","68":"cuda:0","69":"cuda:0","70":"cuda:0","71":"cuda:0","72":"cuda:0","73":"cuda:0","74":"cuda:0","75":"cuda:0","76":"cuda:0","77":"cuda:0","78":"cuda:0","79":"cuda:0","80":"cuda:0","81":"cuda:0","82":"cuda:0","83":"cuda:0","84":"cuda:0","85":"cuda:0","86":"cuda:0","87":"cuda:0","88":"cuda:0","89":"cuda:0","90":"cuda:0","91":"cuda:0","92":"cuda:0","93":"cuda:0","94":"cuda:0","95":"cuda:0","96":"cuda:0","97":"cuda:0","98":"cuda:0","99":"cuda:0","100":"cuda:0","101":"cuda:0","102":"cuda:0","103":"cuda:0","104":"cuda:0","105":"cuda:0","106":"cuda:0","107":"cuda:0","108":"cuda:0","109":"cuda:0","110":"cuda:0","111":"cuda:0","112":"cuda:0","113":"cuda:0","114":"cuda:0","115":"cuda:0","116":"cuda:0","117":"cuda:0","118":"cuda:0","119":"cuda:0","120":"cuda:0","121":"cuda:0","122":"cuda:0","123":"cuda:0","124":"cuda:0","125":"cuda:0","126":"cuda:0","127":"cuda:0","128":"cuda:0","129":"cuda:0","130":"cuda:0","131":"cuda:0","132":"cuda:0","133":"cuda:0","134":"cuda:0","135":"cuda:0","136":"cuda:0","137":"cuda:0","138":"cuda:0","139":"cuda:0","140":"cuda:0","141":"cuda:0","142":"cuda:0","143":"cuda:0","144":"cuda:0","145":"cuda:0","146":"cuda:0","147":"cuda:0","148":"cuda:0","149":"cuda:0","150":"cuda:0","151":"cuda:0","152":"cuda:0","153":"cuda:0","154":"cuda:0","155":"cuda:0","156":"cuda:0","157":"cuda:0","158":"cuda:0","159":"cuda:0","160":"cuda:0","161":"cuda:0","162":"cuda:0","163":"cuda:0","164":"cuda:0","165":"cuda:0","166":"cuda:0","167":"cuda:0","168":"cuda:0","169":"cuda:0","170":"cuda:0","171":"cuda:0","172":"cuda:0","173":"cuda:0","174":"cuda:0","175":"cuda:0","176":"cuda:0","177":"cuda:0","178":"cuda:0","179":"cuda:0","180":"cuda:0","181":"cuda:0","182":"cuda:0","183":"cuda:0","184":"cuda:0","185":"cuda:0","186":"cuda:0","187":"cuda:0","188":"cuda:0","189":"cuda:0","190":"cuda:0","191":"cuda:0","192":"cuda:0","193":"cuda:0","194":"cuda:0","195":"cuda:0","196":"cuda:0","197":"cuda:0","198":"cuda:0","199":"cuda:0","200":"cuda:0","201":"cuda:0","202":"cuda:0","203":"cuda:0","204":"cuda:0","205":"cuda:0","206":"cuda:0","207":"cuda:0","208":"cuda:0","209":"cuda:0","210":"cuda:0","211":"cuda:0","212":"cuda:0","213":"cuda:0","214":"cuda:0","215":"cuda:0","216":"cuda:0","217":"cuda:0","218":"cuda:0","219":"cuda:0","220":"cuda:0","221":"cuda:0","222":"cuda:0","223":"cuda:0","224":"cuda:0","225":"cuda:0","226":"cuda:0","227":"cuda:0","228":"cuda:0","229":"cuda:0","230":"cuda:0","231":"cuda:0","232":"cuda:0","233":"cuda:0","234":"cuda:0","235":"cuda:0","236":"cuda:0","237":"cuda:0","238":"cuda:0","239":"cuda:0","240":"cuda:0","241":"cuda:0","242":"cuda:0","243":"cuda:0","244":"cuda:0","245":"cuda:0","246":"cuda:0","247":"cuda:0","248":"cuda:0","249":"cuda:0","250":"cuda:0","251":"cuda:0","252":"cuda:0","253":"cuda:0","254":"cuda:0","255":"cuda:0","256":"cuda:0","257":"cuda:0","258":"cuda:0","259":"cuda:0","260":"cuda:0","261":"cuda:0","262":"cuda:0","263":"cuda:0","264":"cuda:0","265":"cuda:0","266":"cuda:0","267":"cuda:0","268":"cuda:0","269":"cuda:0","270":"cuda:0","271":"cuda:0","272":"cuda:0","273":"cuda:0","274":"cuda:0","275":"cuda:0","276":"cuda:0","277":"cuda:0","278":"cuda:0","279":"cuda:0","280":"cuda:0","281":"cuda:0","282":"cuda:0","283":"cuda:0","284":"cuda:0","285":"cuda:0","286":"cuda:0","287":"cuda:0","288":"cuda:0","289":"cuda:0","290":"cuda:0","291":"cuda:0","292":"cuda:0","293":"cuda:0","294":"cuda:0","295":"cuda:0","296":"cuda:0","297":"cuda:0","298":"cuda:0","299":"cuda:0","300":"cuda:0","301":"cuda:0","302":"cuda:0","303":"cuda:0","304":"cuda:0","305":"cuda:0","306":"cuda:0","307":"cuda:0","308":"cuda:0","309":"cuda:0","310":"cuda:0","311":"cuda:0","312":"cuda:0","313":"cuda:0","314":"cuda:0","315":"cuda:0","316":"cuda:0","317":"cuda:0","318":"cuda:0","319":"cuda:0","320":"cuda:0","321":"cuda:0","322":"cuda:0","323":"cuda:0","324":"cuda:0","325":"cuda:0","326":"cuda:0","327":"cuda:0","328":"cuda:0","329":"cuda:0","330":"cuda:0","331":"cuda:0","332":"cuda:0","333":"cuda:0","334":"cuda:0","335":"cuda:0","336":"cuda:0","337":"cuda:0","338":"cuda:0","339":"cuda:0","340":"cuda:0","341":"cuda:0","342":"cuda:0","343":"cuda:0","344":"cuda:0","345":"cuda:0","346":"cuda:0","347":"cuda:0","348":"cuda:0","349":"cuda:0","350":"cuda:0","351":"cuda:0","352":"cuda:0","353":"cuda:0","354":"cuda:0","355":"cuda:0","356":"cuda:0","357":"cuda:0","358":"cuda:0","359":"cuda:0","360":"cuda:0","361":"cuda:0","362":"cuda:0","363":"cuda:0","364":"cuda:0","365":"cuda:0","366":"cuda:0","367":"cuda:0","368":"cuda:0","369":"cuda:0","370":"cuda:0","371":"cuda:0","372":"cuda:0","373":"cuda:0","374":"cuda:0","375":"cuda:0","376":"cuda:0","377":"cuda:0","378":"cuda:0","379":"cuda:0","380":"cuda:0","381":"cuda:0","382":"cuda:0","383":"cuda:0","384":"cuda:0","385":"cuda:0","386":"cuda:0","387":"cuda:0","388":"cuda:0","389":"cuda:0","390":"cuda:0","391":"cuda:0","392":"cuda:0","393":"cuda:0","394":"cuda:0","395":"cuda:0","396":"cuda:0","397":"cuda:0","398":"cuda:0","399":"cuda:0"}}